neomake/__init__.py
neomake/neomake.py
neomake/nmprofiles.py
neomake-0.0.6.dist-info/LICENCE
neomake-0.0.6.dist-info/METADATA
neomake-0.0.6.dist-info/WHEEL
neomake-0.0.6.dist-info/top_level.txt
neomake-0.0.6.dist-info/RECORD
