Metadata-Version: 2.1
Name: neomake
Version: 0.0.6
Summary: A new make script for builds.
Author-email: Random World Studio <pointer-to-bios@outlook.com>
Project-URL: Homepage, https://github.com/pointertobios/neomake.git
Classifier: Programming Language :: Python :: 3
Classifier: License :: OSI Approved :: MIT License
Classifier: Operating System :: OS Independent
Requires-Python: >=3.7
License-File: LICENCE
